{"nodes": [{"id": "mercado_alien_index_game", "label": "Mercado Alien (Game)", "file_type": "code", "source_file": "Mercado Alien/index.html", "source_location": null, "source_url": null, "captured_at": null, "author": null, "contributor": null}], "edges": [{"source": "mercado_alien_index_game", "target": "utils_audio_js", "relation": "references", "confidence": "EXTRACTED", "confidence_score": 1.0, "source_file": "Mercado Alien/index.html", "source_location": "line 244", "weight": 1.0}, {"source": "mercado_alien_index_game", "target": "utils_score_js", "relation": "references", "confidence": "EXTRACTED", "confidence_score": 1.0, "source_file": "Mercado Alien/index.html", "source_location": "line 245", "weight": 1.0}, {"source": "mercado_alien_index_game", "target": "utils_elapsed_js", "relation": "references", "confidence": "EXTRACTED", "confidence_score": 1.0, "source_file": "Mercado Alien/index.html", "source_location": "line 246", "weight": 1.0}, {"source": "mercado_alien_index_game", "target": "concept_vanilla_js_spa", "relation": "implements", "confidence": "EXTRACTED", "confidence_score": 1.0, "source_file": "Mercado Alien/index.html", "source_location": "line 247", "weight": 1.0}, {"source": "mercado_alien_index_game", "target": "concept_shield_lives_system", "relation": "implements", "confidence": "EXTRACTED", "confidence_score": 1.0, "source_file": "Mercado Alien/index.html", "source_location": "lines 170-180", "weight": 1.0}, {"source": "mercado_alien_index_game", "target": "concept_timer_bar", "relation": "implements", "confidence": "EXTRACTED", "confidence_score": 1.0, "source_file": "Mercado Alien/index.html", "source_location": "lines 91-108", "weight": 1.0}], "hyperedges": []}